akatsuki_kafka/__init__.py
akatsuki_kafka/consumer.py
akatsuki_kafka/producer.py
akatsuki_kafka-0.1.1.dist-info/METADATA
akatsuki_kafka-0.1.1.dist-info/WHEEL
akatsuki_kafka-0.1.1.dist-info/top_level.txt
akatsuki_kafka-0.1.1.dist-info/RECORD
